[
  {
    "severity": "low",
    "message": "ℹ️ 当前共有 500 个持币地址（模拟数据）",
    "address": null,
    "rank": null,
    "amount": null,
    "timestamp": "2026-03-26T02:17:07.056Z"
  },
  {
    "severity": "medium",
    "message": "📈 大户变动：#10 地址买入 1.00M 代币",
    "address": "0x0bf50b3ff11e84216fdd880ed17c4197edfd8425",
    "rank": 10,
    "amount": 1.0028280774372291,
    "timestamp": "2026-03-26T01:31:26.485Z"
  },
  {
    "severity": "high",
    "message": "🔴 超大庄家地址：#1 地址持有 15.5824% 的代币",
    "address": "0x8fa6f20704330b8533f55e6b298607da57a6b1e5",
    "rank": 1,
    "amount": 15582390.69,
    "timestamp": "2026-03-26T01:17:07.056Z"
  },
  {
    "severity": "medium",
    "message": "📊 前100地址集中度：91.17%，流动性较为集中",
    "address": "0x8fa6f20704330b8533f55e6b298607da57a6b1e5",
    "rank": 1,
    "amount": 15582390.69,
    "timestamp": "2026-03-26T00:17:07.056Z"
  }
]