[
  {
    "rank": 1,
    "address": "0x8d4ab2a3e89eadfdc729204adf863a0bfc7746f6",
    "balance": "140447.52",
    "percentage": "31.2301",
    "change_24h": 0,
    "raw_data": {
      "balance": "140447522388559055260316",
      "is_contract": true
    }
  },
  {
    "rank": 2,
    "address": "0xc1a6fbedae68e1472dbb91fe29b51f7a0bd44f97",
    "balance": "88348.27",
    "percentage": "19.6452",
    "change_24h": 0,
    "raw_data": {
      "balance": "88348265472840232345806",
      "is_contract": true
    }
  },
  {
    "rank": 3,
    "address": "0x46a830062405992852186b904af5ac321a50d684",
    "balance": "87960.31",
    "percentage": "19.5590",
    "change_24h": 0,
    "raw_data": {
      "balance": "87960310653277722637823",
      "is_contract": false
    }
  },
  {
    "rank": 4,
    "address": "0xeee260644e8891a28e2de8b5319cd4b00a4a2191",
    "balance": "75118.10",
    "percentage": "16.7033",
    "change_24h": 0,
    "raw_data": {
      "balance": "75118102742276381360941",
      "is_contract": false
    }
  },
  {
    "rank": 5,
    "address": "0xed0526c047edecbcbd9cd7531c2ea86cf9566f5d",
    "balance": "8065.89",
    "percentage": "1.7935",
    "change_24h": 0,
    "raw_data": {
      "balance": "8065894029147477386227",
      "is_contract": false
    }
  },
  {
    "rank": 6,
    "address": "0xc024d81e80b010b7f941aca53e9d2af7f588d5fc",
    "balance": "7093.73",
    "percentage": "1.5774",
    "change_24h": 0,
    "raw_data": {
      "balance": "7093727024644407894498",
      "is_contract": false
    }
  },
  {
    "rank": 7,
    "address": "0x97b9d2102a9a65a26e1ee82d59e42d1b73b68689",
    "balance": "7022.04",
    "percentage": "1.5614",
    "change_24h": 0,
    "raw_data": {
      "balance": "7022042508990169000000",
      "is_contract": false
    }
  },
  {
    "rank": 8,
    "address": "0xd3e0341b361134014e0c89378b3e36bc5020cd97",
    "balance": "6209.98",
    "percentage": "1.3809",
    "change_24h": 0,
    "raw_data": {
      "balance": "6209978973107694608023",
      "is_contract": false
    }
  },
  {
    "rank": 9,
    "address": "0x0e86aaf378c4082c1ede2448b0f30c24b1e0e5fc",
    "balance": "5840.07",
    "percentage": "1.2986",
    "change_24h": 0,
    "raw_data": {
      "balance": "5840073138193857183753",
      "is_contract": true
    }
  },
  {
    "rank": 10,
    "address": "0xefbe446ebfdd3a7af1818e2525b55dfe3ddd4799",
    "balance": "1701.00",
    "percentage": "0.3782",
    "change_24h": 0,
    "raw_data": {
      "balance": "1700997010000000000000",
      "is_contract": false
    }
  },
  {
    "rank": 11,
    "address": "0x95c54255e8e0c5b95d6ea16b97843ce00fce6153",
    "balance": "1626.31",
    "percentage": "0.3616",
    "change_24h": 0,
    "raw_data": {
      "balance": "1626311833554227154900",
      "is_contract": false
    }
  },
  {
    "rank": 12,
    "address": "0x47cde51bfe78bc08d7a1db86ba5fcc7cdc04114e",
    "balance": "1580.31",
    "percentage": "0.3514",
    "change_24h": 0,
    "raw_data": {
      "balance": "1580313493200000000000",
      "is_contract": false
    }
  },
  {
    "rank": 13,
    "address": "0x9266f125fb2ecb730d9953b46de9c32e2fa83e4a",
    "balance": "1554.05",
    "percentage": "0.3456",
    "change_24h": 0,
    "raw_data": {
      "balance": "1554045694932061424979",
      "is_contract": false
    }
  },
  {
    "rank": 14,
    "address": "0x17a30350771d02409046a683b18fe1c13ccfc4a8",
    "balance": "1531.68",
    "percentage": "0.3406",
    "change_24h": 0,
    "raw_data": {
      "balance": "1531683322256333699710",
      "is_contract": true
    }
  },
  {
    "rank": 15,
    "address": "0x8037292105d46ae56d4fb06a2df6188930fa01de",
    "balance": "1000.00",
    "percentage": "0.2224",
    "change_24h": 0,
    "raw_data": {
      "balance": "1000000000000000000000",
      "is_contract": false
    }
  },
  {
    "rank": 16,
    "address": "0x1a563a16b8d72414b93f21021bd4784afa654768",
    "balance": "1000.00",
    "percentage": "0.2224",
    "change_24h": 0,
    "raw_data": {
      "balance": "999999598015598297771",
      "is_contract": false
    }
  },
  {
    "rank": 17,
    "address": "0xfbc5a98a1358ba1ba8a9e2eebe94e6e3c9b6df24",
    "balance": "1000.00",
    "percentage": "0.2224",
    "change_24h": 0,
    "raw_data": {
      "balance": "999998060000000000000",
      "is_contract": false
    }
  },
  {
    "rank": 18,
    "address": "0x947ba15d0c9ec51057b1061297da112ecfd6af25",
    "balance": "988.51",
    "percentage": "0.2198",
    "change_24h": 0,
    "raw_data": {
      "balance": "988513571955452475490",
      "is_contract": false
    }
  },
  {
    "rank": 19,
    "address": "0x98c827c428f76e5fe6519d77f471c3a4d22f6f0f",
    "balance": "968.93",
    "percentage": "0.2155",
    "change_24h": 0,
    "raw_data": {
      "balance": "968931163528700000000",
      "is_contract": false
    }
  },
  {
    "rank": 20,
    "address": "0xafecbbcca163d63f8c4b3b170adb12892a772f33",
    "balance": "516.98",
    "percentage": "0.1150",
    "change_24h": 0,
    "raw_data": {
      "balance": "516981032664207317147",
      "is_contract": false
    }
  },
  {
    "rank": 21,
    "address": "0xdacadddf821ce45523d0ca0ef14623894044647f",
    "balance": "504.38",
    "percentage": "0.1122",
    "change_24h": 0,
    "raw_data": {
      "balance": "504383158663791915905",
      "is_contract": false
    }
  },
  {
    "rank": 22,
    "address": "0x53a560dc781dd9cecdf14d60e8225a17ef4ac4e3",
    "balance": "501.57",
    "percentage": "0.1115",
    "change_24h": 0,
    "raw_data": {
      "balance": "501572770264734185647",
      "is_contract": false
    }
  },
  {
    "rank": 23,
    "address": "0x46162f7fadd5f3245300a1986ab4610666c57f65",
    "balance": "500.35",
    "percentage": "0.1113",
    "change_24h": 0,
    "raw_data": {
      "balance": "500350197159976189300",
      "is_contract": false
    }
  },
  {
    "rank": 24,
    "address": "0x64f667d79c9a106f26ecfab49e64dd78e7446e6a",
    "balance": "496.18",
    "percentage": "0.1103",
    "change_24h": 0,
    "raw_data": {
      "balance": "496183300000000000000",
      "is_contract": false
    }
  },
  {
    "rank": 25,
    "address": "0x15548f3cf8bbd98969bc0e5551335326054d6078",
    "balance": "354.79",
    "percentage": "0.0789",
    "change_24h": 0,
    "raw_data": {
      "balance": "354787183061775613497",
      "is_contract": false
    }
  },
  {
    "rank": 26,
    "address": "0xaaa3bfb53d5d5116faedc5dd457531f8465f78af",
    "balance": "354.74",
    "percentage": "0.0789",
    "change_24h": 0,
    "raw_data": {
      "balance": "354742419363510491776",
      "is_contract": false
    }
  },
  {
    "rank": 27,
    "address": "0x2f4ba8a9d9daf9a9c82b003b641298469c5aad48",
    "balance": "353.53",
    "percentage": "0.0786",
    "change_24h": 0,
    "raw_data": {
      "balance": "353529308117499725932",
      "is_contract": false
    }
  },
  {
    "rank": 28,
    "address": "0xe1121ccfaa8d454cb77beb38001451b4ebe52445",
    "balance": "351.52",
    "percentage": "0.0782",
    "change_24h": 0,
    "raw_data": {
      "balance": "351518898752550496966",
      "is_contract": false
    }
  },
  {
    "rank": 29,
    "address": "0xf48ff5ab00ab033aaba98c8568072ab01a987566",
    "balance": "350.82",
    "percentage": "0.0780",
    "change_24h": 0,
    "raw_data": {
      "balance": "350818004454113564849",
      "is_contract": false
    }
  },
  {
    "rank": 30,
    "address": "0x38e470d2f88ac99a9d12e54e8a41c917655f0635",
    "balance": "291.06",
    "percentage": "0.0647",
    "change_24h": 0,
    "raw_data": {
      "balance": "291061747142252965748",
      "is_contract": false
    }
  },
  {
    "rank": 31,
    "address": "0x3353b59ce199c667f18fb8c13c640b2ae98273d2",
    "balance": "288.81",
    "percentage": "0.0642",
    "change_24h": 0,
    "raw_data": {
      "balance": "288813856997943407213",
      "is_contract": false
    }
  },
  {
    "rank": 32,
    "address": "0x7b7825c1f25cba1b5dbb119c54f39475e175a969",
    "balance": "281.70",
    "percentage": "0.0626",
    "change_24h": 0,
    "raw_data": {
      "balance": "281697062871868223359",
      "is_contract": false
    }
  },
  {
    "rank": 33,
    "address": "0x6625be6fe3735721c7dc65cb723da8aa8c4e8af4",
    "balance": "280.66",
    "percentage": "0.0624",
    "change_24h": 0,
    "raw_data": {
      "balance": "280664366691583975809",
      "is_contract": true
    }
  },
  {
    "rank": 34,
    "address": "0x199b8f1f8e4a71a8b1595aa50daba17970407497",
    "balance": "274.34",
    "percentage": "0.0610",
    "change_24h": 0,
    "raw_data": {
      "balance": "274336023623895219175",
      "is_contract": false
    }
  },
  {
    "rank": 35,
    "address": "0x8782163068c7cd74d2510768a61135c1e4eb07b3",
    "balance": "218.00",
    "percentage": "0.0485",
    "change_24h": 0,
    "raw_data": {
      "balance": "217997000000000000000",
      "is_contract": false
    }
  },
  {
    "rank": 36,
    "address": "0x47fbbd7af79f53430923bf05220ab3416277b862",
    "balance": "217.72",
    "percentage": "0.0484",
    "change_24h": 0,
    "raw_data": {
      "balance": "217718616552181407448",
      "is_contract": false
    }
  },
  {
    "rank": 37,
    "address": "0x5869458f360d8c1ce49e35fccb3d0a1f25e8d533",
    "balance": "214.65",
    "percentage": "0.0477",
    "change_24h": 0,
    "raw_data": {
      "balance": "214647527607883060925",
      "is_contract": false
    }
  },
  {
    "rank": 38,
    "address": "0x862687eafba7a988148ef563f830e8b66fddfd8b",
    "balance": "214.59",
    "percentage": "0.0477",
    "change_24h": 0,
    "raw_data": {
      "balance": "214589684656071938374",
      "is_contract": false
    }
  },
  {
    "rank": 39,
    "address": "0xee367d7e1151fc6d22f505738954d426eea9136d",
    "balance": "214.55",
    "percentage": "0.0477",
    "change_24h": 0,
    "raw_data": {
      "balance": "214554334544625160838",
      "is_contract": true
    }
  },
  {
    "rank": 40,
    "address": "0xe798a9404143f1aba9d751e2454cb5c1a573363e",
    "balance": "184.36",
    "percentage": "0.0410",
    "change_24h": 0,
    "raw_data": {
      "balance": "184361000000000000000",
      "is_contract": false
    }
  },
  {
    "rank": 41,
    "address": "0xf6fb2a7f3f85aaf1bff9205465a051b537a7fd7c",
    "balance": "182.13",
    "percentage": "0.0405",
    "change_24h": 0,
    "raw_data": {
      "balance": "182126403930674141159",
      "is_contract": false
    }
  },
  {
    "rank": 42,
    "address": "0x095a9fb7a06a5a9e28f0fcbe7ce04abd38017091",
    "balance": "179.94",
    "percentage": "0.0400",
    "change_24h": 0,
    "raw_data": {
      "balance": "179942581799241500466",
      "is_contract": false
    }
  },
  {
    "rank": 43,
    "address": "0x5beed0516cbf1857183c9fe25179eb3b3c2fdf43",
    "balance": "179.72",
    "percentage": "0.0400",
    "change_24h": 0,
    "raw_data": {
      "balance": "179724606715061208281",
      "is_contract": false
    }
  },
  {
    "rank": 44,
    "address": "0x853d61d82842f93a15b185d211ce652a7a5203e9",
    "balance": "179.63",
    "percentage": "0.0399",
    "change_24h": 0,
    "raw_data": {
      "balance": "179629155807567480484",
      "is_contract": false
    }
  },
  {
    "rank": 45,
    "address": "0x6dacc69a92fc4fd56bd290dcb2eb411886ca9289",
    "balance": "154.02",
    "percentage": "0.0342",
    "change_24h": 0,
    "raw_data": {
      "balance": "154015833723014231060",
      "is_contract": false
    }
  },
  {
    "rank": 46,
    "address": "0xefab758bd44ca80d770f17839747af91f50d8468",
    "balance": "153.18",
    "percentage": "0.0341",
    "change_24h": 0,
    "raw_data": {
      "balance": "153181339615176369743",
      "is_contract": false
    }
  },
  {
    "rank": 47,
    "address": "0x9167902a148075f61fa03957e5f4196d18aee5a7",
    "balance": "152.85",
    "percentage": "0.0340",
    "change_24h": 0,
    "raw_data": {
      "balance": "152854000000000000000",
      "is_contract": false
    }
  },
  {
    "rank": 48,
    "address": "0x8609473f9cf4f07b3106ec862418bcdfd76d0e45",
    "balance": "151.79",
    "percentage": "0.0338",
    "change_24h": 0,
    "raw_data": {
      "balance": "151787566732055818921",
      "is_contract": false
    }
  },
  {
    "rank": 49,
    "address": "0x8437abb337b0675c76cefeaef33e10ce2792865b",
    "balance": "151.51",
    "percentage": "0.0337",
    "change_24h": 0,
    "raw_data": {
      "balance": "151513856602997157760",
      "is_contract": true
    }
  },
  {
    "rank": 50,
    "address": "0x1e3e8f0851caf247b50d48a8bba72cda26ea7e5b",
    "balance": "135.17",
    "percentage": "0.0301",
    "change_24h": 0,
    "raw_data": {
      "balance": "135174357391714607298",
      "is_contract": false
    }
  },
  {
    "rank": 51,
    "address": "0xae3dcb1f371f762d1f3bd9348f76ce1e8105ba28",
    "balance": "134.58",
    "percentage": "0.0299",
    "change_24h": 0,
    "raw_data": {
      "balance": "134576164340000000000",
      "is_contract": false
    }
  },
  {
    "rank": 52,
    "address": "0x3291a4913458be74228cabce82944abf390cb16f",
    "balance": "131.72",
    "percentage": "0.0293",
    "change_24h": 0,
    "raw_data": {
      "balance": "131722000000000000000",
      "is_contract": false
    }
  },
  {
    "rank": 53,
    "address": "0x8f2c60ba450c5acf58ea06feb38cfacfe0d9c78a",
    "balance": "129.61",
    "percentage": "0.0288",
    "change_24h": 0,
    "raw_data": {
      "balance": "129609984757642569348",
      "is_contract": false
    }
  },
  {
    "rank": 54,
    "address": "0xde64ddc0c056d00d05e8d3809924e01f8f92ade2",
    "balance": "113.63",
    "percentage": "0.0253",
    "change_24h": 0,
    "raw_data": {
      "balance": "113625546179445455912",
      "is_contract": false
    }
  },
  {
    "rank": 55,
    "address": "0xf265ab17ff7264f3673a64b738510c84cbccabd5",
    "balance": "113.58",
    "percentage": "0.0253",
    "change_24h": 0,
    "raw_data": {
      "balance": "113580398152293752041",
      "is_contract": false
    }
  },
  {
    "rank": 56,
    "address": "0x9132ae29d66143df7d3424587d7032b580b4c52b",
    "balance": "113.46",
    "percentage": "0.0252",
    "change_24h": 0,
    "raw_data": {
      "balance": "113459723098698258581",
      "is_contract": false
    }
  },
  {
    "rank": 57,
    "address": "0x1f1e4e3b02268d87d3b6f9043f3b4d96ab244e34",
    "balance": "113.36",
    "percentage": "0.0252",
    "change_24h": 0,
    "raw_data": {
      "balance": "113362939647383652304",
      "is_contract": false
    }
  },
  {
    "rank": 58,
    "address": "0x877ec2d9718226ef47856e6a98370f65ffec3ecd",
    "balance": "113.09",
    "percentage": "0.0251",
    "change_24h": 0,
    "raw_data": {
      "balance": "113094582790778524454",
      "is_contract": false
    }
  },
  {
    "rank": 59,
    "address": "0xcd4f5fccdab360d4e156d87f45290a6f806ab66e",
    "balance": "102.53",
    "percentage": "0.0228",
    "change_24h": 0,
    "raw_data": {
      "balance": "102534496423737440167",
      "is_contract": false
    }
  },
  {
    "rank": 60,
    "address": "0x6f24eb89b046145b68ff55ca51342609ea436341",
    "balance": "102.23",
    "percentage": "0.0227",
    "change_24h": 0,
    "raw_data": {
      "balance": "102233240451483189248",
      "is_contract": false
    }
  },
  {
    "rank": 61,
    "address": "0x12ed741096c2fac04ca10df54ea04f281def6b01",
    "balance": "102.06",
    "percentage": "0.0227",
    "change_24h": 0,
    "raw_data": {
      "balance": "102062415473727171272",
      "is_contract": false
    }
  },
  {
    "rank": 62,
    "address": "0xe7ae3f6110df7f0f0417055472a9da8702967b00",
    "balance": "101.63",
    "percentage": "0.0226",
    "change_24h": 0,
    "raw_data": {
      "balance": "101631061288688144839",
      "is_contract": false
    }
  },
  {
    "rank": 63,
    "address": "0x9fd197f67538f6f23a5cb4d114cbf07db0aa76e0",
    "balance": "101.34",
    "percentage": "0.0225",
    "change_24h": 0,
    "raw_data": {
      "balance": "101338741383964354618",
      "is_contract": false
    }
  },
  {
    "rank": 64,
    "address": "0x140c9fa014db55645a4be8d84e0e8ab432928106",
    "balance": "90.60",
    "percentage": "0.0201",
    "change_24h": 0,
    "raw_data": {
      "balance": "90599755949413748327",
      "is_contract": false
    }
  },
  {
    "rank": 65,
    "address": "0xb3a3bdb817a453f0f4214579e6cf4f88d512227e",
    "balance": "90.55",
    "percentage": "0.0201",
    "change_24h": 0,
    "raw_data": {
      "balance": "90552305494283740359",
      "is_contract": false
    }
  },
  {
    "rank": 66,
    "address": "0xc92a23068ad2d17ea209c050fb19b319311b0935",
    "balance": "90.54",
    "percentage": "0.0201",
    "change_24h": 0,
    "raw_data": {
      "balance": "90538000000000000000",
      "is_contract": false
    }
  },
  {
    "rank": 67,
    "address": "0x07b94700e51d1a750ea2b808427e1a3df8891770",
    "balance": "90.23",
    "percentage": "0.0201",
    "change_24h": 0,
    "raw_data": {
      "balance": "90226350653358920875",
      "is_contract": false
    }
  },
  {
    "rank": 68,
    "address": "0xe377f394204d4441bf87e351da14a5c6df71db30",
    "balance": "90.10",
    "percentage": "0.0200",
    "change_24h": 0,
    "raw_data": {
      "balance": "90096702906230897090",
      "is_contract": false
    }
  },
  {
    "rank": 69,
    "address": "0x0d74d273a4d2971e7cb8e7acb25ccfe149e37465",
    "balance": "76.06",
    "percentage": "0.0169",
    "change_24h": 0,
    "raw_data": {
      "balance": "76058409113153648318",
      "is_contract": false
    }
  },
  {
    "rank": 70,
    "address": "0x8b3453b96c6267dbf22f559fb8dd9f522722d065",
    "balance": "75.94",
    "percentage": "0.0169",
    "change_24h": 0,
    "raw_data": {
      "balance": "75935889651138996465",
      "is_contract": false
    }
  }
]